<?xml version="1.0" encoding="UTF-8"?><DataFlowResults FileFormatVersion="102" TerminationState="DataFlowOutOfMemory"><Results><Result><Sink Statement="virtualinvoke $r1.&lt;android.os.Bundle: void putParcelable(java.lang.String,android.os.Parcelable)&gt;(&quot;android:support:fragments&quot;, $r5)" Method="&lt;androidx.fragment.app.d: void onSaveInstanceState(android.os.Bundle)&gt;"><AccessPath Value="$r5" Type="androidx.fragment.app.o" TaintSubFields="true"><Fields><Field Value="&lt;androidx.fragment.app.o: androidx.fragment.app.b[] d&gt;" Type="androidx.fragment.app.b[]"></Field><Field Value="&lt;androidx.fragment.app.b: java.util.ArrayList n&gt;" Type="java.util.ArrayList"></Field></Fields></AccessPath></Sink><Sources><Source Statement="$d1 = virtualinvoke $r1.&lt;android.location.Location: double getLongitude()&gt;()" Method="&lt;androidx.appcompat.app.n: void f(android.location.Location)&gt;"><AccessPath Value="$d1" Type="double" TaintSubFields="true"></AccessPath></Source><Source Statement="$d0 = virtualinvoke $r1.&lt;android.location.Location: double getLatitude()&gt;()" Method="&lt;androidx.appcompat.app.n: void f(android.location.Location)&gt;"><AccessPath Value="$d0" Type="double" TaintSubFields="true"></AccessPath></Source><Source Statement="$d1 = virtualinvoke $r1.&lt;android.location.Location: double getLongitude()&gt;()" Method="&lt;androidx.appcompat.app.n: void f(android.location.Location)&gt;"><AccessPath Value="$d1" Type="double" TaintSubFields="true"></AccessPath></Source><Source Statement="$d0 = virtualinvoke $r1.&lt;android.location.Location: double getLatitude()&gt;()" Method="&lt;androidx.appcompat.app.n: void f(android.location.Location)&gt;"><AccessPath Value="$d0" Type="double" TaintSubFields="true"></AccessPath></Source></Sources></Result><Result><Sink Statement="staticinvoke &lt;android.util.Log: int d(java.lang.String,java.lang.String)&gt;(&quot;FragmentManager&quot;, $r3)" Method="&lt;androidx.fragment.app.m: void A0(androidx.fragment.app.Fragment,int)&gt;"><AccessPath Value="$r3" Type="java.lang.String" TaintSubFields="true"></AccessPath></Sink><Sources><Source Statement="$d1 = virtualinvoke $r1.&lt;android.location.Location: double getLongitude()&gt;()" Method="&lt;androidx.appcompat.app.n: void f(android.location.Location)&gt;"><AccessPath Value="$d1" Type="double" TaintSubFields="true"></AccessPath></Source><Source Statement="$d1 = virtualinvoke $r1.&lt;android.location.Location: double getLongitude()&gt;()" Method="&lt;androidx.appcompat.app.n: void f(android.location.Location)&gt;"><AccessPath Value="$d1" Type="double" TaintSubFields="true"></AccessPath></Source><Source Statement="$d0 = virtualinvoke $r1.&lt;android.location.Location: double getLatitude()&gt;()" Method="&lt;androidx.appcompat.app.n: void f(android.location.Location)&gt;"><AccessPath Value="$d0" Type="double" TaintSubFields="true"></AccessPath></Source><Source Statement="$d0 = virtualinvoke $r1.&lt;android.location.Location: double getLatitude()&gt;()" Method="&lt;androidx.appcompat.app.n: void f(android.location.Location)&gt;"><AccessPath Value="$d0" Type="double" TaintSubFields="true"></AccessPath></Source><Source Statement="$d1 = virtualinvoke $r1.&lt;android.location.Location: double getLongitude()&gt;()" Method="&lt;androidx.appcompat.app.n: void f(android.location.Location)&gt;"><AccessPath Value="$d1" Type="double" TaintSubFields="true"></AccessPath></Source><Source Statement="$d0 = virtualinvoke $r1.&lt;android.location.Location: double getLatitude()&gt;()" Method="&lt;androidx.appcompat.app.n: void f(android.location.Location)&gt;"><AccessPath Value="$d0" Type="double" TaintSubFields="true"></AccessPath></Source></Sources></Result></Results><PerformanceData><PerformanceEntry Name="CallgraphConstructionSeconds" Value="9"></PerformanceEntry><PerformanceEntry Name="TaintPropagationSeconds" Value="91"></PerformanceEntry><PerformanceEntry Name="PathReconstructionSeconds" Value="10"></PerformanceEntry><PerformanceEntry Name="TotalRuntimeSeconds" Value="111"></PerformanceEntry><PerformanceEntry Name="MaxMemoryConsumption" Value="3028"></PerformanceEntry><PerformanceEntry Name="SourceCount" Value="8"></PerformanceEntry><PerformanceEntry Name="SinkCount" Value="124"></PerformanceEntry></PerformanceData></DataFlowResults>